aerofs-4.0.7.dist-info/METADATA
aerofs-4.0.7.dist-info/WHEEL
aerofs-4.0.7.dist-info/licenses/LICENSE
aerofs/__init__.py
aerofs/__init__.pyi
aerofs/_aerofs.abi3.so
aerofs/os.py
aerofs/os.pyi
aerofs/py.typed
aerofs/tempfile.py
aerofs/tempfile.pyi
aerofs/threadpool.py
aerofs/threadpool.pyi
aerofs/threadpool/__init__.py
aerofs-4.0.7.dist-info/RECORD
