Metadata-Version: 2.4
Name: aerofs
Version: 4.0.7
Classifier: Development Status :: 4 - Beta
Classifier: Intended Audience :: Developers
Classifier: License :: OSI Approved :: Apache Software License
Classifier: Programming Language :: Python :: 3
Classifier: Programming Language :: Python :: 3.9
Classifier: Programming Language :: Python :: 3.10
Classifier: Programming Language :: Python :: 3.11
Classifier: Programming Language :: Python :: 3.12
Classifier: Programming Language :: Python :: 3.13
Classifier: Programming Language :: Rust
Classifier: Operating System :: OS Independent
Classifier: Topic :: Software Development :: Libraries :: Python Modules
Classifier: Framework :: AsyncIO
Requires-Dist: pytest>=7.0 ; extra == 'dev'
Requires-Dist: pytest-asyncio>=0.21 ; extra == 'dev'
Requires-Dist: pytest-cov>=4.0 ; extra == 'dev'
Provides-Extra: dev
License-File: LICENSE
Summary: High-Performance Asynchronous File I/O for Python, powered by Rust
Keywords: async,file,io,rust,tokio,performance
Author-email: ohmyarthur <cp@hylcyn.xyz>
Requires-Python: >=3.9
Project-URL: Homepage, https://github.com/ohmyarthur/aerofs
Project-URL: Repository, https://github.com/ohmyarthur/aerofs
Project-URL: Issues, https://github.com/ohmyarthur/aerofs/issues
